opencodr/__init__.py
opencodr/agent.py
opencodr/app_meta.py
opencodr/async_typer.py
opencodr/config.py
opencodr/console.py
opencodr/display.py
opencodr/main.py
opencodr/mcp_client.py
opencodr/mcp_server.py
opencodr/types.py
opencodr/workspace.py
opencodr/assets/dockerfile.base
assets/dockerfile.base
opencodr-0.1.9.dist-info/METADATA
opencodr-0.1.9.dist-info/WHEEL
opencodr-0.1.9.dist-info/entry_points.txt
opencodr-0.1.9.dist-info/RECORD
