Metadata-Version: 2.4
Name: opencodr
Version: 0.1.9
Summary: open source terminal-based coding agent
Author-email: notpolomarco@icloud.com
Requires-Python: >=3.13
Requires-Dist: aiofiles==24.1.0
Requires-Dist: aiohappyeyeballs==2.4.6
Requires-Dist: aiohttp==3.11.13
Requires-Dist: aiosignal==1.3.2
Requires-Dist: annotated-types==0.7.0
Requires-Dist: anyio==4.8.0
Requires-Dist: attrs==25.1.0
Requires-Dist: certifi==2025.1.31
Requires-Dist: charset-normalizer==3.4.1
Requires-Dist: click==8.1.8
Requires-Dist: debugpy==1.8.12
Requires-Dist: distro==1.9.0
Requires-Dist: docstring-parser==0.16
Requires-Dist: filelock==3.17.0
Requires-Dist: frozenlist==1.5.0
Requires-Dist: fsspec==2025.2.0
Requires-Dist: h11==0.14.0
Requires-Dist: httpcore==1.0.7
Requires-Dist: httpx-sse==0.4.0
Requires-Dist: httpx==0.28.1
Requires-Dist: huggingface-hub==0.29.2
Requires-Dist: idna==3.10
Requires-Dist: importlib-metadata==8.6.1
Requires-Dist: jinja2==3.1.5
Requires-Dist: jiter==0.8.2
Requires-Dist: jsonschema-specifications==2024.10.1
Requires-Dist: jsonschema==4.23.0
Requires-Dist: litellm==1.63.0
Requires-Dist: markdown-it-py==3.0.0
Requires-Dist: markupsafe==3.0.2
Requires-Dist: mcp>=1.4.1
Requires-Dist: mdurl==0.1.2
Requires-Dist: multidict==6.1.0
Requires-Dist: openai==1.65.2
Requires-Dist: packaging==24.2
Requires-Dist: platformdirs>=4.3.6
Requires-Dist: prompt-toolkit==3.0.50
Requires-Dist: propcache==0.3.0
Requires-Dist: pydantic-core==2.27.2
Requires-Dist: pydantic-settings==2.8.1
Requires-Dist: pydantic==2.10.6
Requires-Dist: pygments==2.19.1
Requires-Dist: python-dotenv==1.0.1
Requires-Dist: pyyaml==6.0.2
Requires-Dist: questionary==2.1.0
Requires-Dist: referencing==0.36.2
Requires-Dist: regex==2024.11.6
Requires-Dist: requests==2.32.3
Requires-Dist: rich==13.9.4
Requires-Dist: rpds-py==0.23.1
Requires-Dist: shellingham==1.5.4
Requires-Dist: sniffio==1.3.1
Requires-Dist: sse-starlette==2.2.1
Requires-Dist: starlette==0.46.0
Requires-Dist: tenacity==9.0.0
Requires-Dist: tiktoken==0.9.0
Requires-Dist: tokenizers==0.21.0
Requires-Dist: tqdm==4.67.1
Requires-Dist: typer==0.15.2
Requires-Dist: typing-extensions==4.12.2
Requires-Dist: urllib3==2.3.0
Requires-Dist: uvicorn==0.34.0
Requires-Dist: wcwidth==0.2.13
Requires-Dist: yarl==1.18.3
Requires-Dist: zipp==3.21.0
